playready_utils/__init__.py
playready_utils/bcert.py
playready_utils/license/definitions.py
playready_utils/license/main.py
playready_utils/license/structs.py
playready_utils/main.py
playready_utils/prd.py
playready_utils/pssh.py
playready_utils-0.3.5.dist-info/entry_points.txt
playready_utils-0.3.5.dist-info/LICENSE
playready_utils-0.3.5.dist-info/METADATA
playready_utils-0.3.5.dist-info/WHEEL
playready_utils-0.3.5.dist-info/RECORD
