Metadata-Version: 2.3
Name: playready_utils
Version: 0.3.5
Summary: Tools built to work with PlayReady and pyplayready
License: CC BY-NC-ND 4.0
Keywords: playready,tools,pyplayready
Author: 8c
Requires-Python: >=3.8,<4.0
Classifier: Development Status :: 3 - Alpha
Classifier: Intended Audience :: Developers
Classifier: License :: Other/Proprietary License
Classifier: Natural Language :: English
Classifier: Operating System :: OS Independent
Classifier: Programming Language :: Python :: 3
Classifier: Programming Language :: Python :: 3.8
Classifier: Programming Language :: Python :: 3.9
Classifier: Programming Language :: Python :: 3.10
Classifier: Programming Language :: Python :: 3.11
Classifier: Programming Language :: Python :: 3.12
Classifier: Programming Language :: Python :: 3.13
Classifier: Topic :: Software Development :: Libraries :: Python Modules
Requires-Dist: cloup (>=0.14.1)
Requires-Dist: coloredlogs (>=15.0.1,<16.0.0)
Requires-Dist: construct (==2.8.8)
Project-URL: Issues, https://github.com/8c/playready-utils/issues
Project-URL: Repository, https://github.com/8c/playready-utils
